CHANGELOG.md
MANIFEST.in
README.md
setup.cfg
setup.py
rpi_dht22_exporter/app.py
rpi_dht22_exporter/main.py
rpi_dht22_exporter/metrics.py
rpi_dht22_exporter.egg-info/PKG-INFO
rpi_dht22_exporter.egg-info/SOURCES.txt
rpi_dht22_exporter.egg-info/dependency_links.txt
rpi_dht22_exporter.egg-info/entry_points.txt
rpi_dht22_exporter.egg-info/requires.txt
rpi_dht22_exporter.egg-info/top_level.txt
test/__init__.py
test/test_app.py
test/test_main.py