Metadata-Version: 2.1
Name: rpi-dht22-exporter
Version: 2.0.1
Summary: UNKNOWN
Home-page: https://github.com/urbas/rpi-dht22-exporter
Author: Matej Urbas
Author-email: matej.urbas@gmail.com
License: MIT license
Keywords: rpi-dht22-exporter,dht22,prometheus,exporter
Platform: UNKNOWN
